agents/__init__.py
ai_smart_contract_auditor-1.0.4.dist-info/licenses/LICENSE
features/__init__.py
features/code4rena_filter.py
features/fix_suggester.py
features/poc_generator.py
features/report_generator.py
features/risk_scorer.py
memory/__init__.py
memory/vector_db.py
parallel/__init__.py
parallel/parallel_audit.py
parallel/parallel_database.py
parallel/parallel_processor.py
tools/4naly3er_wrapper.py
tools/__init__.py
tools/foundry_wrapper.py
tools/slither_wrapper.py
training/__init__.py
training/custom_training.py
utils/__init__.py
utils/checkpoints.py
utils/solodit_mcp_client_poc.py
utils/solodit_scraper.py
utils/solodit_scraper_selenium.py
ai_smart_contract_auditor-1.0.4.dist-info/METADATA
ai_smart_contract_auditor-1.0.4.dist-info/WHEEL
ai_smart_contract_auditor-1.0.4.dist-info/entry_points.txt
ai_smart_contract_auditor-1.0.4.dist-info/top_level.txt
ai_smart_contract_auditor-1.0.4.dist-info/RECORD
