Metadata-Version: 2.4
Name: ai-smart-contract-auditor
Version: 1.0.4
Summary: AI-powered smart contract security auditor with parallel processing
Home-page: https://github.com/jw3b-dev/AI-Smart-Contract-Auditor
Author: AI Smart Contract Auditor Team
Author-email: contact@example.com
Project-URL: Bug Tracker, https://github.com/jw3b-dev/AI-Smart-Contract-Auditor/issues
Project-URL: Documentation, https://github.com/jw3b-dev/AI-Smart-Contract-Auditor#readme
Project-URL: Source Code, https://github.com/jw3b-dev/AI-Smart-Contract-Auditor
Keywords: smart-contract security audit blockchain ethereum solidity
Classifier: Development Status :: 4 - Beta
Classifier: Intended Audience :: Developers
Classifier: Topic :: Security
Classifier: Topic :: Software Development :: Quality Assurance
Classifier: License :: OSI Approved :: MIT License
Classifier: Programming Language :: Python :: 3
Classifier: Programming Language :: Python :: 3.9
Classifier: Programming Language :: Python :: 3.10
Classifier: Programming Language :: Python :: 3.11
Classifier: Operating System :: OS Independent
Requires-Python: >=3.9
License-File: LICENSE
Requires-Dist: slither-analyzer>=0.10.0
Requires-Dist: halmos>=0.1.0
Requires-Dist: langchain>=0.1.0
Requires-Dist: langchain-openai>=0.0.5
Requires-Dist: openai>=1.0.0
Requires-Dist: chromadb>=0.4.0
Requires-Dist: sentence-transformers>=2.3.0
Requires-Dist: selenium>=4.16.0
Requires-Dist: webdriver-manager>=4.0.0
Requires-Dist: beautifulsoup4>=4.12.0
Requires-Dist: pandas>=2.0.0
Requires-Dist: numpy>=1.24.0
Requires-Dist: requests>=2.31.0
Requires-Dist: python-dotenv>=1.0.0
Requires-Dist: pyyaml>=6.0
Requires-Dist: pydantic>=2.5.0
Requires-Dist: pytest>=7.4.0
Requires-Dist: pytest-asyncio>=0.21.0
Requires-Dist: pytest-xdist>=3.0.0
Requires-Dist: pytest-cov>=4.0.0
Requires-Dist: pytest-benchmark>=4.0.0
Requires-Dist: hypothesis>=6.0.0
Requires-Dist: faker>=18.0.0
Dynamic: author
Dynamic: author-email
Dynamic: classifier
Dynamic: description
Dynamic: description-content-type
Dynamic: home-page
Dynamic: keywords
Dynamic: license-file
Dynamic: project-url
Dynamic: requires-dist
Dynamic: requires-python
Dynamic: summary
